GFDLWS/__init__.py
GFDLWS/exchangemessages.py
GFDLWS/exchanges.py
GFDLWS/exchangesnapshot.py
GFDLWS/expirydates.py
GFDLWS/history.py
GFDLWS/historyaftermarket.py
GFDLWS/historygreeks.py
GFDLWS/instruments.py
GFDLWS/instrumentsonsearch.py
GFDLWS/instrumenttypes.py
GFDLWS/lastquote.py
GFDLWS/lastquotearray.py
GFDLWS/lastquotearrayoptiongreeks.py
GFDLWS/lastquotearrayshort.py
GFDLWS/lastquotearrayshortclose.py
GFDLWS/lastquoteoptionchain.py
GFDLWS/lastquoteoptiongreeks.py
GFDLWS/lastquoteoptiongreekschain.py
GFDLWS/lastquoteshort.py
GFDLWS/lastquoteshortclose.py
GFDLWS/limitation.py
GFDLWS/marketmessages.py
GFDLWS/optiontypes.py
GFDLWS/products.py
GFDLWS/quote.py
GFDLWS/realsnapshot.py
GFDLWS/realtime.py
GFDLWS/realtimegreeks.py
GFDLWS/serverinfo.py
GFDLWS/snapshot.py
GFDLWS/strikeprices.py
GFDLWS/subscribeoptionchain.py
GFDLWS/subscribeoptionchaingreeks.py
GFDLWS/subscribetopgainerslosers.py
GFDLWS/topgainerslosers.py
GFDLWS/ws.py
GFDLWS-0.0.4.dist-info/METADATA
GFDLWS-0.0.4.dist-info/WHEEL
GFDLWS-0.0.4.dist-info/top_level.txt
GFDLWS-0.0.4.dist-info/RECORD
